README
setup.py
django_tastypie_with_uploads_dummycache_error500.egg-info/PKG-INFO
django_tastypie_with_uploads_dummycache_error500.egg-info/SOURCES.txt
django_tastypie_with_uploads_dummycache_error500.egg-info/dependency_links.txt
django_tastypie_with_uploads_dummycache_error500.egg-info/requires.txt
django_tastypie_with_uploads_dummycache_error500.egg-info/top_level.txt
tastypie/__init__.py
tastypie/admin.py
tastypie/api.py
tastypie/authentication.py
tastypie/authorization.py
tastypie/bundle.py
tastypie/cache.py
tastypie/constants.py
tastypie/exceptions.py
tastypie/fields.py
tastypie/http.py
tastypie/models.py
tastypie/paginator.py
tastypie/resources.py
tastypie/serializers.py
tastypie/throttle.py
tastypie/validation.py
tastypie/management/__init__.py
tastypie/management/commands/__init__.py
tastypie/management/commands/backfill_api_keys.py
tastypie/utils/__init__.py
tastypie/utils/dict.py
tastypie/utils/formatting.py
tastypie/utils/mime.py
tastypie/utils/urls.py
tastypie/utils/validate_jsonp.py