Metadata-Version: 1.1
Name: django-tastypie-with-uploads-dummycache-error500
Version: 1.0.0-beta-red1
Summary: Patched version of Django Tastypie -- check README.rst.
Home-page: http://github.com/toastdriven/django-tastypie/
Author: Daniel Lindsley
Author-email: daniel@toastdriven.com
License: UNKNOWN
Platform: UNKNOWN
Classifier: Development Status :: 4 - Beta
Classifier: Environment :: Web Environment
Classifier: Framework :: Django
Classifier: Intended Audience :: Developers
Classifier: License :: OSI Approved :: BSD License
Classifier: Operating System :: OS Independent
Classifier: Programming Language :: Python
Classifier: Topic :: Utilities
Requires: mimeparse
Requires: python_dateutil(>=1.5, < 2.0)
